
{
  "https://w3id.org/steel/ProcessOntology/AbsoluteCrossheadTravel" : {
    "http://www.w3.org/1999/02/22-rdf-syntax-ns#type" : [ {
        "value" : "http://www.w3.org/2002/07/owl#Class",
        "type" : "uri"
        }
      ,
      {
        "value" : "http://www.w3.org/2004/02/skos/core#Concept",
        "type" : "uri"
        }
      
      ],
    "http://www.w3.org/2000/01/rdf-schema#comment" : [ {
        "value" : "Absolute position der Traverse",
        "lang" : "de",
        "type" : "literal"
        }
      ,
      {
        "value" : "Absolute position of the crosshead.",
        "lang" : "en",
        "type" : "literal"
        }
      
      ],
    "http://www.w3.org/2000/01/rdf-schema#label" : [ {
        "value" : "AbsoluteCrossheadTravel",
        "lang" : "en",
        "type" : "literal"
        }
      
      ],
    "http://www.w3.org/2004/02/skos/core#altlabel" : [ {
        "value" : "Absolute crosshead travel",
        "lang" : "en",
        "type" : "literal"
        }
      ,
      {
        "value" : "Traversenweg absolut",
        "lang" : "de",
        "type" : "literal"
        }
      
      ],
    "http://www.w3.org/2004/02/skos/core#preflabel" : [ {
        "value" : "AbsoluteCrossheadTravel",
        "lang" : "en",
        "type" : "literal"
        }
      
      ],
    "https://w3id.org/steel/ProcessOntology/hasDescriptionCitationSource" : [ {
        "value" : "Author",
        "lang" : "de",
        "type" : "literal"
        }
      ,
      {
        "value" : "Authors",
        "lang" : "en",
        "type" : "literal"
        }
      
      ]
    }
  }
